README.rst
setup.py
totango/__init__.py
totango.egg-info/PKG-INFO
totango.egg-info/SOURCES.txt
totango.egg-info/dependency_links.txt
totango.egg-info/not-zip-safe
totango.egg-info/requires.txt
totango.egg-info/top_level.txt