Metadata-Version: 1.0
Name: totango
Version: 0.3.1
Summary: Totango Python Library
Home-page: http://github.com/gbourdin/totango-python
Author: German Bourdin
Author-email: admin@gbourdin.com
License: Apache 2.0
Keywords: totango
Platform: UNKNOWN
